<?xml version="1.0" encoding="utf-8" ?><dwsync><file name="button.js" local="-3705843966495686656" remote="-3645311982694865352" testing="0" /><file name="checkbox.js" local="-3705843966495686656" remote="-3645311982694865352" testing="0" /><file name="form.js" local="-3705843966495686656" remote="-3645311982694865352" testing="0" /><file name="hiddenfield.js" local="-3705843966495686656" remote="-3645311982694865352" testing="0" /><file name="radio.js" local="-3705843966495686656" remote="-3645311982694865352" testing="0" /><file name="select.js" local="-3705843966495686656" remote="-3645311982694865352" testing="0" /><file name="textarea.js" local="-3705843966495686656" remote="-3645311982694865352" testing="0" /><file name="textfield.js" local="-3705843966495686656" remote="-3645311982694865352" testing="0" /></dwsync>